content_summarizer/__init__.py
content_summarizer/cli.py
content_summarizer/core.py
content_summarizer/main.py
content_summarizer/data/__init__.py
content_summarizer/data/data_models.py
content_summarizer/managers/__init__.py
content_summarizer/managers/cache_manager.py
content_summarizer/managers/config_manager.py
content_summarizer/managers/path_manager.py
content_summarizer/processors/__init__.py
content_summarizer/processors/audio_processor.py
content_summarizer/services/__init__.py
content_summarizer/services/summary_service.py
content_summarizer/services/transcription_service.py
content_summarizer/services/video_service_interface.py
content_summarizer/services/youtube_service.py
content_summarizer/utils/__init__.py
content_summarizer/utils/logger_config.py
content_summarizer/utils/warning_config.py
content_summarizer-1.0.4.dist-info/licenses/LICENSE
content_summarizer-1.0.4.dist-info/METADATA
content_summarizer-1.0.4.dist-info/WHEEL
content_summarizer-1.0.4.dist-info/entry_points.txt
content_summarizer-1.0.4.dist-info/top_level.txt
content_summarizer-1.0.4.dist-info/RECORD
