Metadata-Version: 2.4
Name: content-summarizer
Version: 1.0.4
Summary: A command-line tool to summarize YouTube videos using AI.
Author-email: Gabriel Carvalho <contato@gcarvalho.com.br>
License: 
Project-URL: Homepage, https://github.com/GabrielCarvalhoSouza/content_summarizer
Project-URL: Repository, https://github.com/GabrielCarvalhoSouza/content_summarizer
Keywords: youtube,summarizer,ai,gemini,whisper,cli
Classifier: License :: OSI Approved :: Apache Software License
Classifier: Programming Language :: Python :: 3
Classifier: Programming Language :: Python :: 3.11
Classifier: Operating System :: OS Independent
Classifier: Topic :: Utilities
Classifier: Environment :: Console
Requires-Python: <3.12,>=3.11
License-File: LICENSE
Requires-Dist: google-generativeai>=0.8.5
Requires-Dist: python-dotenv>=1.1.0
Requires-Dist: pytubefix>=9.1.2
Requires-Dist: requests>=2.32.4
Requires-Dist: colorlog>=6.9.0
Requires-Dist: faster-whisper>=1.1.1
Requires-Dist: platformdirs>=4.3.8
Requires-Dist: rich>=13.9.4
Provides-Extra: dev
Requires-Dist: ruff; extra == "dev"
Requires-Dist: mypy; extra == "dev"
Dynamic: license-file
